{
  "uniqueId": "BSkyBlock7f013df7-b76a-4711-851e-60a319a1ffaa",
  "level": 403,
  "initialLevel": 0,
  "pointsToNextLevel": 100,
  "uwCount": {},
  "mdCount": {
    "CRAFTING_TABLE": 1,
    "SAND": 16,
    "GOLD_ORE": 4,
    "DIAMOND_ORE": 2,
    "HOPPER": 1,
    "IRON_ORE": 12,
    "BEDROCK": 1,
    "QUARTZ_BLOCK": 193,
    "STONE": 197,
    "DIRT": 50,
    "NETHER_PORTAL": 6,
    "SPAWNER": 2,
    "AIR": 10237078,
    "COBBLESTONE_SLAB": 272,
    "OBSIDIAN": 12,
    "LAVA": 21,
    "WATER": 1321,
    "GRASS_BLOCK": 39,
    "COBBLESTONE": 400,
    "OAK_WALL_SIGN": 15,
    "TUBE_CORAL_BLOCK": 5,
    "SHULKER_BOX": 1,
    "COAL_ORE": 11,
    "HORN_CORAL_BLOCK": 1,
    "GLASS": 287,
    "CHEST": 3,
    "OAK_LEAVES": 12,
    "FURNACE": 1,
    "CACTUS": 8,
    "SUGAR_CANE": 24,
    "STONE_BRICK_SLAB": 38
  }
}