{
  "uniqueId": "BSkyBlockfabb01c5-4465-43b3-b9b4-c6b280259bd3",
  "level": 630,
  "initialLevel": 0,
  "pointsToNextLevel": 2,
  "uwCount": {},
  "mdCount": {
    "OAK_PLANKS": 175,
    "SPAWNER": 1,
    "TORCH": 83,
    "FURNACE": 5,
    "WATER": 192,
    "SHULKER_BOX": 2,
    "GLASS": 585,
    "ENCHANTING_TABLE": 1,
    "BEDROCK": 1,
    "OAK_SLAB": 6,
    "GRASS_BLOCK": 151,
    "AIR": 10234238,
    "SAND": 62,
    "COBBLESTONE_WALL": 28,
    "COBBLESTONE": 826,
    "NETHER_PORTAL": 6,
    "OAK_WALL_SIGN": 16,
    "SPRUCE_SLAB": 252,
    "DAMAGED_ANVIL": 1,
    "CRAFTING_TABLE": 1,
    "BOOKSHELF": 15,
    "STONE_BUTTON": 24,
    "WALL_TORCH": 10,
    "SPRUCE_LEAVES": 111,
    "STONE_BRICKS": 921,
    "HOPPER": 11,
    "OAK_FENCE": 210,
    "SPRUCE_LOG": 114,
    "OBSIDIAN": 14,
    "COBBLESTONE_SLAB": 659,
    "DARK_OAK_FENCE": 24,
    "CHEST": 72,
    "STONE_BRICK_SLAB": 6,
    "OAK_LOG": 99,
    "BREWING_STAND": 1,
    "IRON_BLOCK": 1,
    "CACTUS": 48,
    "DARK_OAK_SLAB": 73,
    "DARK_OAK_PLANKS": 185,
    "SPRUCE_PLANKS": 52,
    "LAVA": 5,
    "TUBE_CORAL_BLOCK": 1,
    "SUGAR_CANE": 42,
    "LANTERN": 6,
    "DARK_OAK_LOG": 172,
    "DIRT": 145,
    "OAK_LEAVES": 347,
    "COAL_ORE": 1
  }
}