{
  "uniqueId": "BSkyBlock57211e73-b178-48a8-92f4-3fe4df8d2615",
  "level": 3088,
  "initialLevel": 3,
  "pointsToNextLevel": 37,
  "uwCount": {},
  "mdCount": {
    "NOTE_BLOCK": 1,
    "SAND": 2,
    "DEAD_HORN_CORAL_BLOCK": 1,
    "IRON_DOOR": 8,
    "GOLD_ORE": 1,
    "BOOKSHELF": 17,
    "BEDROCK": 1,
    "DIRT": 38,
    "NETHER_PORTAL": 6,
    "REDSTONE_BLOCK": 2,
    "AIR": 10229597,
    "COBBLESTONE_SLAB": 30,
    "OBSIDIAN": 10,
    "EMERALD_BLOCK": 33,
    "REDSTONE_WIRE": 48,
    "WATER": 373,
    "OAK_TRAPDOOR": 16,
    "OAK_WALL_SIGN": 58,
    "COBBLESTONE": 830,
    "DIAMOND_BLOCK": 9,
    "CHIPPED_ANVIL": 1,
    "WALL_TORCH": 9,
    "CHEST": 257,
    "TORCH": 138,
    "MAGENTA_WALL_BANNER": 4,
    "IRON_BLOCK": 59,
    "PISTON": 10,
    "VINE": 12,
    "STONE_BRICK_SLAB": 543,
    "STONE_BRICK_STAIRS": 32,
    "CRAFTING_TABLE": 2,
    "COBBLESTONE_STAIRS": 2,
    "BEACON": 1,
    "HOPPER": 119,
    "GOLD_BLOCK": 64,
    "IRON_ORE": 1,
    "OAK_PRESSURE_PLATE": 10,
    "LEVER": 1,
    "CHISELED_STONE_BRICKS": 5,
    "STONE": 4689,
    "REPEATER": 10,
    "SPAWNER": 8,
    "WITHER_SKELETON_WALL_SKULL": 1,
    "HEAVY_WEIGHTED_PRESSURE_PLATE": 7,
    "PISTON_HEAD": 1,
    "SEA_LANTERN": 64,
    "REDSTONE_WALL_TORCH": 11,
    "STICKY_PISTON": 2,
    "LAVA": 15,
    "OAK_FENCE_GATE": 1,
    "STONE_BRICKS": 1985,
    "COMPARATOR": 11,
    "GRASS_BLOCK": 23,
    "DRAGON_WALL_HEAD": 1,
    "QUARTZ_PILLAR": 146,
    "IRON_TRAPDOOR": 3,
    "LADDER": 32,
    "PLAYER_WALL_HEAD": 8,
    "SHULKER_BOX": 1,
    "STONE_BUTTON": 2,
    "HORN_CORAL_BLOCK": 1,
    "STONE_SLAB": 18,
    "GLASS": 604,
    "ENCHANTING_TABLE": 1,
    "FURNACE": 2,
    "STONECUTTER": 1,
    "OAK_FENCE": 1,
    "LIGHT_BLUE_SHULKER_BOX": 4
  }
}