{
  "uniqueId": "BSkyBlockfb745f75-937d-41d9-8937-fe76e0f62973",
  "level": 700,
  "initialLevel": 75,
  "pointsToNextLevel": 27,
  "uwCount": {},
  "mdCount": {
    "STONE_BRICK_SLAB": 1386,
    "OAK_SIGN": 1,
    "REDSTONE_BLOCK": 2,
    "PRISMARINE": 282,
    "STONE_BUTTON": 4,
    "HOPPER": 74,
    "FURNACE": 11,
    "PRISMARINE_SLAB": 292,
    "NETHER_BRICK_FENCE": 52,
    "COBBLESTONE_SLAB": 637,
    "DARK_OAK_SLAB": 36,
    "PLAYER_HEAD": 4,
    "PISTON_HEAD": 3,
    "LAVA": 22,
    "STICKY_PISTON": 63,
    "IRON_DOOR": 4,
    "POWERED_RAIL": 6,
    "DROPPER": 1,
    "OBSIDIAN": 12,
    "OAK_LEAVES": 3082,
    "PRISMARINE_STAIRS": 4,
    "AIR": 10222171,
    "CRAFTING_TABLE": 5,
    "OAK_LOG": 779,
    "STONE": 108,
    "OAK_WALL_SIGN": 22,
    "TORCH": 92,
    "BEDROCK": 1,
    "CHEST": 127,
    "ENCHANTING_TABLE": 1,
    "OAK_PRESSURE_PLATE": 60,
    "COMPARATOR": 2,
    "DIRT": 187,
    "WATER": 821,
    "SAND": 512,
    "BOOKSHELF": 19,
    "RAIL": 24,
    "PLAYER_WALL_HEAD": 3,
    "ANVIL": 1,
    "GRASS_BLOCK": 112,
    "CACTUS": 514,
    "LEVER": 1,
    "STONE_BRICKS": 4077,
    "NETHER_PORTAL": 9,
    "REDSTONE_WALL_TORCH": 2,
    "REPEATER": 62,
    "STONE_BRICK_STAIRS": 55,
    "WALL_TORCH": 122,
    "GLASS": 2045,
    "OAK_FENCE": 483,
    "COBBLESTONE": 1338,
    "SEA_LANTERN": 198,
    "DARK_OAK_PLANKS": 1,
    "COBBLESTONE_WALL": 89,
    "CHIPPED_ANVIL": 1,
    "OAK_FENCE_GATE": 16,
    "REDSTONE_WIRE": 30,
    "SPAWNER": 4
  }
}