{
  "uniqueId": "BSkyBlockf3e64cf3-b340-4b19-8c52-b7f6c16ce576",
  "level": 2627,
  "initialLevel": 0,
  "pointsToNextLevel": 52,
  "uwCount": {},
  "mdCount": {
    "GRASS_BLOCK": 1416,
    "SWEET_BERRY_BUSH": 11,
    "POTATOES": 39,
    "ENCHANTING_TABLE": 1,
    "EMERALD_ORE": 4,
    "OAK_DOOR": 8,
    "NETHER_PORTAL": 6,
    "BLUE_ORCHID": 1,
    "LECTERN": 19,
    "SPRUCE_SAPLING": 2,
    "RAIL": 25,
    "ALLIUM": 1,
    "COBBLESTONE": 4718,
    "BOOKSHELF": 27,
    "STONECUTTER": 1,
    "STONE_BRICK_SLAB": 129,
    "FURNACE": 4,
    "REDSTONE_WALL_TORCH": 1,
    "COBBLESTONE_SLAB": 1293,
    "SPRUCE_STAIRS": 21,
    "REDSTONE_BLOCK": 5,
    "OAK_SLAB": 8,
    "HOPPER": 22,
    "LANTERN": 21,
    "COBBLESTONE_STAIRS": 11,
    "AIR": 10223407,
    "OAK_LOG": 37,
    "BEEHIVE": 1,
    "OBSERVER": 1,
    "REDSTONE_ORE": 10,
    "COAL_ORE": 12,
    "WALL_TORCH": 67,
    "PISTON_HEAD": 5,
    "JUNGLE_PLANKS": 1,
    "OAK_LEAVES": 370,
    "ACACIA_WALL_SIGN": 32,
    "DARK_OAK_STAIRS": 132,
    "LIGHT_GRAY_BED": 2,
    "BAMBOO": 298,
    "LAPIS_ORE": 11,
    "OAK_SAPLING": 5,
    "FARMLAND": 109,
    "PUMPKIN": 1,
    "BEDROCK": 1,
    "LAVA": 8,
    "TRIPWIRE": 1,
    "GRINDSTONE": 1,
    "MELON": 3,
    "PISTON": 3,
    "MELON_STEM": 1,
    "POWERED_RAIL": 8,
    "BREWING_STAND": 1,
    "COBBLESTONE_WALL": 13,
    "JUNGLE_LOG": 3,
    "OAK_FENCE_GATE": 2,
    "OAK_FENCE": 145,
    "VINE": 687,
    "OXEYE_DAISY": 3,
    "BLACK_BED": 8,
    "PINK_TULIP": 1,
    "ORANGE_TULIP": 1,
    "BELL": 2,
    "CORNFLOWER": 1,
    "COMPOSTER": 1,
    "BEETROOTS": 21,
    "LEVER": 2,
    "GOLD_ORE": 25,
    "CHEST": 36,
    "WHITE_TULIP": 1,
    "ATTACHED_MELON_STEM": 3,
    "OAK_PLANKS": 421,
    "RED_TULIP": 1,
    "CRAFTING_TABLE": 3,
    "GRAY_BED": 6,
    "ATTACHED_PUMPKIN_STEM": 1,
    "DANDELION": 2,
    "OAK_TRAPDOOR": 58,
    "STICKY_PISTON": 8,
    "POPPY": 2,
    "OAK_WALL_SIGN": 23,
    "GLASS": 196,
    "SUGAR_CANE": 3,
    "ANVIL": 66,
    "TORCH": 155,
    "DIRT": 93,
    "DIAMOND_ORE": 9,
    "CARROTS": 21,
    "WHITE_BED": 24,
    "BIRCH_SAPLING": 2,
    "REPEATER": 10,
    "BUBBLE_COLUMN": 31,
    "BARREL": 2,
    "SOUL_SAND": 1,
    "PUMPKIN_STEM": 2,
    "BEE_NEST": 2,
    "OBSIDIAN": 12,
    "COMPARATOR": 2,
    "LILY_OF_THE_VALLEY": 1,
    "SPAWNER": 5,
    "CHIPPED_ANVIL": 1,
    "DARK_OAK_SLAB": 1860,
    "SPRUCE_PLANKS": 3,
    "STONE_BRICK_WALL": 322,
    "IRON_ORE": 14,
    "WATER": 2735,
    "WHEAT": 21,
    "REDSTONE_WIRE": 30,
    "STONE_BRICKS": 802,
    "AZURE_BLUET": 1
  }
}