{
  "uniqueId": "BSkyBlock4bf488ab-d0d5-4728-beb5-22dcca000234",
  "level": 3322,
  "initialLevel": 0,
  "pointsToNextLevel": 56,
  "uwCount": {},
  "mdCount": {
    "CORNFLOWER": 1,
    "DIRT": 251,
    "COBBLESTONE": 1277,
    "GRINDSTONE": 1,
    "CACTUS": 6,
    "WATER": 822,
    "IRON_BLOCK": 1,
    "GOLD_ORE": 1,
    "GOLD_BLOCK": 1,
    "FURNACE": 9,
    "STICKY_PISTON": 1,
    "PISTON_HEAD": 3,
    "WHITE_WOOL": 13,
    "IRON_TRAPDOOR": 1,
    "IRON_ORE": 1,
    "NETHER_PORTAL": 6,
    "AIR": 77430319,
    "SMOOTH_STONE": 1007,
    "OAK_FENCE": 143,
    "TORCH": 344,
    "PISTON": 20,
    "SMITHING_TABLE": 1,
    "OAK_SIGN": 2,
    "CRAFTING_TABLE": 1,
    "LAPIS_ORE": 1,
    "DIAMOND_BLOCK": 252,
    "HOPPER": 204,
    "OBSIDIAN": 12,
    "ENCHANTING_TABLE": 1,
    "BEDROCK": 1,
    "LANTERN": 13,
    "OAK_SLAB": 464,
    "ANVIL": 2,
    "OAK_PRESSURE_PLATE": 16,
    "LEVER": 1,
    "PLAYER_HEAD": 1,
    "OAK_LOG": 1,
    "WHITE_BED": 54,
    "OAK_FENCE_GATE": 1,
    "COBBLESTONE_SLAB": 1653,
    "REPEATER": 20,
    "WALL_TORCH": 18,
    "OAK_WALL_SIGN": 26,
    "BOOKSHELF": 17,
    "SMOOTH_STONE_SLAB": 1474,
    "SPAWNER": 5,
    "CHEST": 137,
    "GLASS": 685,
    "REDSTONE_WIRE": 76,
    "COARSE_DIRT": 42,
    "BREWING_STAND": 3,
    "OAK_LEAVES": 1,
    "COAL_ORE": 2,
    "LECTERN": 9,
    "SAND": 2,
    "OAK_PLANKS": 183,
    "GRASS_BLOCK": 399,
    "LAVA": 35,
    "STONE": 4,
    "SMOKER": 3
  }
}