{"stats":{"minecraft:custom":{"minecraft:time_since_rest":38795,"minecraft:open_chest":1,"minecraft:crouch_one_cm":8290,"minecraft:play_one_minute":164834,"minecraft:sprint_one_cm":32539,"minecraft:deaths":3,"minecraft:damage_taken":240,"minecraft:walk_one_cm":57874,"minecraft:sneak_time":4511,"minecraft:walk_under_water_one_cm":88970,"minecraft:drop":2,"minecraft:jump":395,"minecraft:eat_cake_slice":2,"minecraft:leave_game":7,"minecraft:walk_on_water_one_cm":20132,"minecraft:time_since_death":38775,"minecraft:climb_one_cm":1431,"minecraft:fly_one_cm":3072461},"minecraft:picked_up":{"minecraft:ladder":1,"minecraft:sugar_cane":2},"minecraft:used":{"minecraft:brain_coral_block":13,"minecraft:stripped_acacia_wood":8,"minecraft:red_sandstone":207,"minecraft:smooth_red_sandstone_slab":6,"minecraft:fire_coral_block":31,"minecraft:tube_coral_fan":1,"minecraft:tube_coral_block":17,"minecraft:terracotta":4,"minecraft:horn_coral":3,"minecraft:brain_coral_fan":1,"minecraft:lantern":1,"minecraft:bubble_coral_block":20,"minecraft:smooth_red_sandstone":39,"minecraft:ladder":2,"minecraft:orange_wool":3,"minecraft:fire_coral":1,"minecraft:horn_coral_block":53,"minecraft:white_terracotta":69,"minecraft:fire_coral_fan":4,"minecraft:kelp":28,"minecraft:orange_terracotta":2,"minecraft:sugar_cane":61},"minecraft:dropped":{"minecraft:sugar_cane":1,"minecraft:player_head":1}},"DataVersion":2584}